remote_explorer_game/__init__.py
remote_explorer_game/remote_explorer_game.py
remote_explorer_game-1.3.1.dist-info/licenses/LICENSE
remote_explorer_game-1.3.1.dist-info/METADATA
remote_explorer_game-1.3.1.dist-info/WHEEL
remote_explorer_game-1.3.1.dist-info/top_level.txt
remote_explorer_game-1.3.1.dist-info/RECORD
