Metadata-Version: 2.4
Name: remote-explorer-game
Version: 1.3.1
Summary: Client library for the Remote Explorer Game
Author: David Krčmář
License-Expression: MIT
Keywords: game,client,httpx,explorer
Requires-Python: >=3.9
License-File: LICENSE
Requires-Dist: httpx>=0.24
Requires-Dist: numpy>=1.24
Dynamic: license-file
